directory/__init__.py
directory/__main__.py
directory/config.py
directory/configure.py
directory/execution.py
directory/models.py
directory/validation.py
directory/workflows.py
directory/agents/__init__.py
directory/agents/base.py
directory/agents/executor.py
directory/agents/planner.py
directory/agents/query.py
directory/agents/summary.py
directory/text/__init__.py
directory/text/executor_prompt.txt
directory/text/help.txt
directory/text/planner_prompt.txt
directory/text/query_prompt.txt
directory/text/summary_prompt.txt
directory/tui/__init__.py
directory/tui/app.py
directory/tui/directory.tcss
directory/tui/widgets.py
directory_agent-1.0.3.dist-info/licenses/LICENSE
directory_agent-1.0.3.dist-info/METADATA
directory_agent-1.0.3.dist-info/WHEEL
directory_agent-1.0.3.dist-info/entry_points.txt
directory_agent-1.0.3.dist-info/top_level.txt
directory_agent-1.0.3.dist-info/RECORD
