Metadata-Version: 2.4
Name: directory-agent
Version: 1.0.3
Summary: AI-powered filesystem management via natural language
Author: Director.y Contributors
Project-URL: Bug Reports, https://github.com/raytonc/Director.y/issues
Project-URL: Source, https://github.com/raytonc/Director.y
Classifier: Development Status :: 4 - Beta
Classifier: Intended Audience :: Developers
Classifier: License :: OSI Approved :: MIT License
Classifier: Programming Language :: Python :: 3
Classifier: Programming Language :: Python :: 3.11
Classifier: Programming Language :: Python :: 3.12
Classifier: Operating System :: Microsoft :: Windows
Requires-Python: >=3.11
License-File: LICENSE
Requires-Dist: anthropic>=0.40.0
Requires-Dist: pydantic>=2.0.0
Requires-Dist: prompt-toolkit>=3.0.0
Requires-Dist: questionary>=2.0.0
Requires-Dist: textual>=0.90.0
Requires-Dist: tomli>=2.0.0; python_version < "3.11"
Requires-Dist: tomli-w>=1.0.0
Provides-Extra: dev
Requires-Dist: pytest>=7.0.0; extra == "dev"
Requires-Dist: pytest-asyncio>=0.21.0; extra == "dev"
Dynamic: license-file
